.DS_Store
asynctools/__init__.py
asynctools/helpers.py
asynctools/helpers_test.py
aiohttp_asynctools-0.1.3.dist-info/LICENSE
aiohttp_asynctools-0.1.3.dist-info/METADATA
aiohttp_asynctools-0.1.3.dist-info/WHEEL
aiohttp_asynctools-0.1.3.dist-info/top_level.txt
aiohttp_asynctools-0.1.3.dist-info/RECORD
