Metadata-Version: 2.1
Name: aiohttp-asynctools
Version: 0.1.3
Summary: Some function and classes to help you deal with aiohttp sessions
Home-page: https://github.com/cglacet/aiohttp-sessions-helpers
Author: Christian Glacet
Author-email: cglacet@kune.tech
License: MIT
Project-URL: Bug Reports, https://github.com/cglacet/aiohttp-sessions-helpers/issues
Project-URL: Source, https://github.com/cglacet/aiohttp-sessions-helpers/
Platform: UNKNOWN
Classifier: Development Status :: 3 - Alpha
Classifier: Programming Language :: Python :: 3
Classifier: Intended Audience :: Developers
Classifier: License :: OSI Approved :: MIT License
Classifier: Operating System :: OS Independent
Requires-Dist: aiohttp (>=3.3)
Provides-Extra: example
Requires-Dist: aiohttp-jinja2 (>=1.1.1) ; extra == 'example'
